plute/__init__.py
plute/base.py
plute/text/__init__.py
plute/text/features/__init__.py
plute/text/features/regex.py
plute/text/utils/__init__.py
plute/text/utils/utterances.py
plute/types.py
plute-0.0.1.dist-info/LICENSE
plute-0.0.1.dist-info/WHEEL
plute-0.0.1.dist-info/METADATA
plute-0.0.1.dist-info/RECORD
