Metadata-Version: 2.1
Name: plute
Version: 0.0.1
Summary: Framework for building SLU systems
Requires-Python: >=3.8,<4.0
Classifier: Programming Language :: Python :: 3
Classifier: Programming Language :: Python :: 3.8
Requires-Dist: exegr (>=0.1.3,<0.2.0)
Requires-Dist: pydash (>=4.7.6,<5.0.0)
